Workbook

Sheet Executive Summary
A1: SAEIS — Smart Audit & ERP Integration System
A2: 5-Year Financial Model & Key Performance Indicators (2026 - 2030)
B4: TARGET SEED FUNDING | D4: 5-YR CUMULATIVE REVENUE | F4: YEAR 5 NET PROFIT | H4: YEAR 5 EBITDA MARGIN
B5: 26500 | D5: =SUM(Projections!B14:F14) -> #VALUE! | F5: =Projections!F27 -> -52852.5 | H5: =Projections!F25 -> #DIV/0!
A8: Metric ($USD) | B8: Year 1 (2026) | C8: Year 2 (2027) | D8: Year 3 (2028) | E8: Year 4 (2029) | F8: Year 5 (2030)
A9: Active B2B Clients | B9: =Projections!B9 -> 4 | C9: =Projections!C9 -> 17 | D9: =Projections!D9 -> 46 | E9: =Projections!E9 -> 97 | F9: =Projections!F9 -> 180
A10: Total Annual Revenue | B10: =Projections!B14 -> 19200 | C10: =Projections!C14 -> #VALUE! | D10: =Projections!D14 -> 0 | E10: =Projections!E14 -> 0 | F10: =Projections!F14 -> 0
A11: Cost of Goods Sold (COGS) | B11: =Projections!B18 -> 1536 | C11: =Projections!C18 -> #VALUE! | D11: =Projections!D18 -> 0 | E11: =Projections!E18 -> 0 | F11: =Projections!F18 -> 0
A12: Gross Profit | B12: =Projections!B19 -> 17664 | C12: =Projections!C19 -> #VALUE! | D12: =Projections!D19 -> 0 | E12: =Projections!E19 -> 0 | F12: =Projections!F19 -> 0
A13: Operating Expenses (OPEX) | B13: =Projections!B23 -> 18000 | C13: =Projections!C23 -> 26100 | D13: =Projections!D23 -> 35235 | E13: =Projections!E23 -> 44043.75 | F13: =Projections!F23 -> 52852.5
A14: EBITDA | B14: =Projections!B24 -> -336 | C14: =Projections!C24 -> #VALUE! | D14: =Projections!D24 -> -35235 | E14: =Projections!E24 -> -44043.75 | F14: =Projections!F24 -> -52852.5
A15: Net Profit | B15: =Projections!B27 -> -336 | C15: =Projections!C27 -> #VALUE! | D15: =Projections!D27 -> -35235 | E15: =Projections!E27 -> -44043.75 | F15: =Projections!F27 -> -52852.5
A16: Net Profit Margin % | B16: =Projections!B28 -> -0.0175 | C16: =Projections!C28 -> #VALUE! | D16: =Projections!D28 -> #DIV/0! | E16: =Projections!E28 -> #DIV/0! | F16: =Projections!F28 -> #DIV/0!

Sheet Assumptions
A1: Key Financial Assumptions & Revenue Drivers
A4: 1. Pricing & Tier Structure ($USD)
A5: Starter Tier Annual Subscription | B5: 2400 | C5: Small entities / basic ERP integration
A6: Professional Tier Annual Subscription | B6: 6000 | C6: Mid-sized enterprises / multi-module ERP
A7: Enterprise Tier Annual Subscription | B7: 15000 | C7: Large groups / custom audit rules & APIs
A8: One-time Setup & Integration Fee | B8: 1500 | C8: Average deployment fee per client
A10: 2. Customer Acquisition Ramp (Active Clients)
A11: Client Segment | B11: Y1 (2026) | C11: Y2 (2027) | D11: Y3 (2028) | E11: Y4 (2029) | F11: Y5 (2030)
A12: Starter Tier Clients | B12: 3 | C12: 10 | D12: 25 | E12: 50 | F12: 90
A13: Professional Tier Clients | B13: 1 | C13: 5 | D13: 15 | E13: 35 | F13: 65
A14: Enterprise Tier Clients | B14: 0 | C14: 2 | D14: 6 | E14: 12 | F14: 25
A16: 3. Cost Ratios & Operational Drivers
A17: Cloud Infrastructure & Hosting (% Rev) | B17: 0.08 | C17: AWS / Azure server costs & scaling
A18: Base Operating Expenses Year 1 | B18: 18000 | C18: Initial salaries, legal, software licenses
A19: Corporate Tax Rate | B19: 0.15 | C19: Statutory tax assumption on taxable income

Sheet Projections
A1: SAEIS — 5-Year Pro-Forma Income Statement
A4: Line Item ($USD) | B4: Year 1 (2026) | C4: Year 2 (2027) | D4: Year 3 (2028) | E4: Year 4 (2029) | F4: Year 5 (2030)
A5: CLIENT ACQUISITION RAMP
A6: Starter Tier Clients | B6: =Assumptions!B12 -> 3 | C6: =Assumptions!C12 -> 10 | D6: =Assumptions!D12 -> 25 | E6: =Assumptions!E12 -> 50 | F6: =Assumptions!F12 -> 90
A7: Professional Tier Clients | B7: =Assumptions!B13 -> 1 | C7: =Assumptions!C13 -> 5 | D7: =Assumptions!D13 -> 15 | E7: =Assumptions!E13 -> 35 | F7: =Assumptions!F13 -> 65
A8: Enterprise Tier Clients | B8: =Assumptions!B14 -> 0 | C8: =Assumptions!C14 -> 2 | D8: =Assumptions!D14 -> 6 | E8: =Assumptions!E14 -> 12 | F8: =Assumptions!F14 -> 25
A9: Total Active Clients | B9: =SUM(B6:B8) -> 4 | C9: =SUM(C6:C8) -> 17 | D9: =SUM(D6:D8) -> 46 | E9: =SUM(E6:E8) -> 97 | F9: =SUM(F6:F8) -> 180
A11: REVENUE STREAM ($USD)
A12: Recurring SaaS Subscriptions | B12: =B6*Assumptions!$B$5 + B7*Assumptions!$B$6 + B8*Assumptions!$B$7 -> 13200 | C12: =C6*Assumptions!$C$5 + C7*Assumptions!$C$6 + C8*Assumptions!$C$7 -> #VALUE! | D12: =D6*Assumptions!$D$5 + D7*Assumptions!$D$6 + D8*Assumptions!$D$7 -> 0 | E12: =E6*Assumptions!$E$5 + E7*Assumptions!$E$6 + E8*Assumptions!$E$7 -> 0 | F12: =F6*Assumptions!$F$5 + F7*Assumptions!$F$6 + F8*Assumptions!$F$7 -> 0
A13: Implementation & Setup Fees | B13: =(B6+B7+B8)*Assumptions!$B$8 -> 6000 | C13: =(C6+C7+C8)*Assumptions!$C$8 -> #VALUE! | D13: =(D6+D7+D8)*Assumptions!$D$8 -> 0 | E13: =(E6+E7+E8)*Assumptions!$E$8 -> 0 | F13: =(F6+F7+F8)*Assumptions!$F$8 -> 0
A14: Total Revenue | B14: =B12+B13 -> 19200 | C14: =C12+C13 -> #VALUE! | D14: =D12+D13 -> 0 | E14: =E12+E13 -> 0 | F14: =F12+F13 -> 0
A16: COST OF GOODS SOLD (COGS)
A17: Cloud Hosting & API Expenses | B17: =B14*Assumptions!$B$17 -> 1536 | C17: =C14*Assumptions!$C$17 -> #VALUE! | D17: =D14*Assumptions!$D$17 -> 0 | E17: =E14*Assumptions!$E$17 -> 0 | F17: =F14*Assumptions!$F$17 -> 0
A18: Total COGS | B18: =B17 -> 1536 | C18: =C17 -> #VALUE! | D18: =D17 -> 0 | E18: =E17 -> 0 | F18: =F17 -> 0
A19: GROSS PROFIT | B19: =B14-B18 -> 17664 | C19: =C14-C18 -> #VALUE! | D19: =D14-D18 -> 0 | E19: =E14-E18 -> 0 | F19: =F14-F18 -> 0
A20: Gross Margin % | B20: =B19/B14 -> 0.92 | C20: =C19/C14 -> #VALUE! | D20: =D19/D14 -> #DIV/0! | E20: =E19/E14 -> #DIV/0! | F20: =F19/F14 -> #DIV/0!
A22: OPERATING EXPENSES (OPEX)
A23: R&D, Salaries, Sales & Marketing | B23: =Assumptions!$B$18 -> 18000 | C23: =B23*1.45 -> 26100 | D23: =C23*1.35 -> 35235 | E23: =D23*1.25 -> 44043.75 | F23: =E23*1.2 -> 52852.5
A24: EBITDA | B24: =B19-B23 -> -336 | C24: =C19-C23 -> #VALUE! | D24: =D19-D23 -> -35235 | E24: =E19-E23 -> -44043.75 | F24: =F19-F23 -> -52852.5
A25: EBITDA Margin % | B25: =B24/B14 -> -0.0175 | C25: =C24/C14 -> #VALUE! | D25: =D24/D14 -> #DIV/0! | E25: =E24/E14 -> #DIV/0! | F25: =F24/F14 -> #DIV/0!
A26: Tax Expense (15%) | B26: =IF(B24>0, B24*Assumptions!$B$19, 0) -> 0 | C26: =IF(C24>0, C24*Assumptions!$C$19, 0) -> #VALUE! | D26: =IF(D24>0, D24*Assumptions!$D$19, 0) -> 0 | E26: =IF(E24>0, E24*Assumptions!$E$19, 0) -> 0 | F26: =IF(F24>0, F24*Assumptions!$F$19, 0) -> 0
A27: NET PROFIT | B27: =B24-B26 -> -336 | C27: =C24-C26 -> #VALUE! | D27: =D24-D26 -> -35235 | E27: =E24-E26 -> -44043.75 | F27: =F24-F26 -> -52852.5
A28: Net Margin % | B28: =B27/B14 -> -0.0175 | C28: =C27/C14 -> #VALUE! | D28: =D27/D14 -> #DIV/0! | E28: =E27/E14 -> #DIV/0! | F28: =F27/F14 -> #DIV/0!

Sheet Use of Funds
A1: Seed Round Investment & Budget Allocation ($26,500)
A4: Category / Expenditure | B4: Allocation % | C4: Amount ($USD) | D4: Strategic Objective
A5: Core Engineering & ERP Integration | B5: 0.4 | C5: 10600 | D5: Completing Onyx Pro / SQL live connectors & audit engine
A6: Legal Setup & Regional Expansion (Riyadh) | B6: 0.3 | C6: 7950 | D6: Incorporation in Saudi Arabia, Flat6Labs accelerator alignment
A7: B2B Marketing & Client Acquisition | B7: 0.2 | C7: 5300 | D7: Targeted outreach to accounting firms & medium enterprises
A8: Working Capital & Contingency Reserve | B8: 0.1 | C8: 2650 | D8: Operational buffer and cloud infrastructure prepayment
A9: Total Seed Round Target | B9: =SUM(B5:B8) -> 1 | C9: =SUM(C5:C8) -> 26500
